py_docker
