Metadata-Version: 2.1
Name: cleandev-py-docker
Version: 0.1.1
Summary: Wrapper de resumenes de docker modo cluster
Home-page: UNKNOWN
Author: Daniel Rodriguez Rodriguez
Author-email: danielrodriguezrodriguez.pks@gmail.com
License: UNKNOWN
Platform: UNKNOWN
Classifier: Programming Language :: Python :: 3
Classifier: License :: OSI Approved :: MIT License
Classifier: Operating System :: OS Independent
Requires-Python: >=3.9
